fsplib/Dataset.py
fsplib/ExpandingWindowCV.py
fsplib/Model.py
fsplib/SlidingWindowCV.py
fsplib/__init__.py
fsplib-0.0.3.dist-info/METADATA
fsplib-0.0.3.dist-info/WHEEL
fsplib-0.0.3.dist-info/top_level.txt
fsplib-0.0.3.dist-info/RECORD
