Metadata-Version: 2.1
Name: fsplib
Version: 0.0.3
Summary: python package for PredictFutureSales compet
Requires-Python: >=3.7
